Workbook

Sheet Dashboard
B2: BUDGET TRACKER
B3: Financial Analytics Dashboard
B6: GESAMTGUTHABEN | D6: EINNAHMEN · MONAT | F6: AUSGABEN · MONAT | H6: BILANZ · MONAT | J6: SPARQUOTE · MONAT
B7: =Konten!G15 | D7: =SUMPRODUCT((Transaktionen!D4:D500="Einnahme")*(MONTH(Transaktionen!C4:C500)=MONTH(TODAY()))*(YEAR(Transaktionen!C4:C500)=YEAR(TODAY()))*Transaktionen!E4:E500) | F7: =SUMPRODUCT((Transaktionen!D4:D500="Ausgabe")*(MONTH(Transaktionen!C4:C500)=MONTH(TODAY()))*(YEAR(Transaktionen!C4:C500)=YEAR(TODAY()))*Transaktionen!E4:E500) | H7: =D7-F7 | J7: =IF(D7=0,0,(D7-F7)/D7)
B10: MONATSÜBERSICHT | H10: BUDGET STATUS
B11: Einnahmen vs. Ausgaben pro Monat | H11: Ausgaben vs. Budget (aktueller Monat)
H12: Kategorie | I12: Budget | J12: Ausgegeben | K12: Status
B13: Jan | C13: =SUMPRODUCT((Transaktionen!D$4:D$500="Einnahme")*(MONTH(Transaktionen!C$4:C$500)=1)*(YEAR(Transaktionen!C$4:C$500)=YEAR(TODAY()))*Transaktionen!E$4:E$500) | D13: =SUMPRODUCT((Transaktionen!D$4:D$500="Ausgabe")*(MONTH(Transaktionen!C$4:C$500)=1)*(YEAR(Transaktionen!C$4:C$500)=YEAR(TODAY()))*Transaktionen!E$4:E$500) | E13: =C13-D13 | F13: =IF(C13=0,0,E13/C13) | H13: =IF(Budgets!B4="","",Budgets!B4) | I13: =IF(H13="","",Budgets!C4) | J13: =IF(H13="","",SUMPRODUCT((Transaktionen!D$4:D$500="Ausgabe")*(Transaktionen!F$4:F$500=H13)*(MONTH(Transaktionen!C$4:C$500)=MONTH(TODAY()))*(YEAR(Transaktionen!C$4:C$500)=YEAR(TODAY()))*Transaktionen!E$4:E$500)) | K13: =IF(OR(H13="",I13=0),"",IF(J13/I13>1,"OVER",IF(J13/I13>0.8,"WARN",TEXT(J13/I13,"0%"))))
B14: Feb | C14: =SUMPRODUCT((Transaktionen!D$4:D$500="Einnahme")*(MONTH(Transaktionen!C$4:C$500)=2)*(YEAR(Transaktionen!C$4:C$500)=YEAR(TODAY()))*Transaktionen!E$4:E$500) | D14: =SUMPRODUCT((Transaktionen!D$4:D$500="Ausgabe")*(MONTH(Transaktionen!C$4:C$500)=2)*(YEAR(Transaktionen!C$4:C$500)=YEAR(TODAY()))*Transaktionen!E$4:E$500) | E14: =C14-D14 | F14: =IF(C14=0,0,E14/C14) | H14: =IF(Budgets!B5="","",Budgets!B5) | I14: =IF(H14="","",Budgets!C5) | J14: =IF(H14="","",SUMPRODUCT((Transaktionen!D$4:D$500="Ausgabe")*(Transaktionen!F$4:F$500=H14)*(MONTH(Transaktionen!C$4:C$500)=MONTH(TODAY()))*(YEAR(Transaktionen!C$4:C$500)=YEAR(TODAY()))*Transaktionen!E$4:E$500)) | K14: =IF(OR(H14="",I14=0),"",IF(J14/I14>1,"OVER",IF(J14/I14>0.8,"WARN",TEXT(J14/I14,"0%"))))
B15: Mär | C15: =SUMPRODUCT((Transaktionen!D$4:D$500="Einnahme")*(MONTH(Transaktionen!C$4:C$500)=3)*(YEAR(Transaktionen!C$4:C$500)=YEAR(TODAY()))*Transaktionen!E$4:E$500) | D15: =SUMPRODUCT((Transaktionen!D$4:D$500="Ausgabe")*(MONTH(Transaktionen!C$4:C$500)=3)*(YEAR(Transaktionen!C$4:C$500)=YEAR(TODAY()))*Transaktionen!E$4:E$500) | E15: =C15-D15 | F15: =IF(C15=0,0,E15/C15) | H15: =IF(Budgets!B6="","",Budgets!B6) | I15: =IF(H15="","",Budgets!C6) | J15: =IF(H15="","",SUMPRODUCT((Transaktionen!D$4:D$500="Ausgabe")*(Transaktionen!F$4:F$500=H15)*(MONTH(Transaktionen!C$4:C$500)=MONTH(TODAY()))*(YEAR(Transaktionen!C$4:C$500)=YEAR(TODAY()))*Transaktionen!E$4:E$500)) | K15: =IF(OR(H15="",I15=0),"",IF(J15/I15>1,"OVER",IF(J15/I15>0.8,"WARN",TEXT(J15/I15,"0%"))))
B16: Apr | C16: =SUMPRODUCT((Transaktionen!D$4:D$500="Einnahme")*(MONTH(Transaktionen!C$4:C$500)=4)*(YEAR(Transaktionen!C$4:C$500)=YEAR(TODAY()))*Transaktionen!E$4:E$500) | D16: =SUMPRODUCT((Transaktionen!D$4:D$500="Ausgabe")*(MONTH(Transaktionen!C$4:C$500)=4)*(YEAR(Transaktionen!C$4:C$500)=YEAR(TODAY()))*Transaktionen!E$4:E$500) | E16: =C16-D16 | F16: =IF(C16=0,0,E16/C16) | H16: =IF(Budgets!B7="","",Budgets!B7) | I16: =IF(H16="","",Budgets!C7) | J16: =IF(H16="","",SUMPRODUCT((Transaktionen!D$4:D$500="Ausgabe")*(Transaktionen!F$4:F$500=H16)*(MONTH(Transaktionen!C$4:C$500)=MONTH(TODAY()))*(YEAR(Transaktionen!C$4:C$500)=YEAR(TODAY()))*Transaktionen!E$4:E$500)) | K16: =IF(OR(H16="",I16=0),"",IF(J16/I16>1,"OVER",IF(J16/I16>0.8,"WARN",TEXT(J16/I16,"0%"))))
B17: Mai | C17: =SUMPRODUCT((Transaktionen!D$4:D$500="Einnahme")*(MONTH(Transaktionen!C$4:C$500)=5)*(YEAR(Transaktionen!C$4:C$500)=YEAR(TODAY()))*Transaktionen!E$4:E$500) | D17: =SUMPRODUCT((Transaktionen!D$4:D$500="Ausgabe")*(MONTH(Transaktionen!C$4:C$500)=5)*(YEAR(Transaktionen!C$4:C$500)=YEAR(TODAY()))*Transaktionen!E$4:E$500) | E17: =C17-D17 | F17: =IF(C17=0,0,E17/C17) | H17: =IF(Budgets!B8="","",Budgets!B8) | I17: =IF(H17="","",Budgets!C8) | J17: =IF(H17="","",SUMPRODUCT((Transaktionen!D$4:D$500="Ausgabe")*(Transaktionen!F$4:F$500=H17)*(MONTH(Transaktionen!C$4:C$500)=MONTH(TODAY()))*(YEAR(Transaktionen!C$4:C$500)=YEAR(TODAY()))*Transaktionen!E$4:E$500)) | K17: =IF(OR(H17="",I17=0),"",IF(J17/I17>1,"OVER",IF(J17/I17>0.8,"WARN",TEXT(J17/I17,"0%"))))
B18: Jun | C18: =SUMPRODUCT((Transaktionen!D$4:D$500="Einnahme")*(MONTH(Transaktionen!C$4:C$500)=6)*(YEAR(Transaktionen!C$4:C$500)=YEAR(TODAY()))*Transaktionen!E$4:E$500) | D18: =SUMPRODUCT((Transaktionen!D$4:D$500="Ausgabe")*(MONTH(Transaktionen!C$4:C$500)=6)*(YEAR(Transaktionen!C$4:C$500)=YEAR(TODAY()))*Transaktionen!E$4:E$500) | E18: =C18-D18 | F18: =IF(C18=0,0,E18/C18) | H18: =IF(Budgets!B9="","",Budgets!B9) | I18: =IF(H18="","",Budgets!C9) | J18: =IF(H18="","",SUMPRODUCT((Transaktionen!D$4:D$500="Ausgabe")*(Transaktionen!F$4:F$500=H18)*(MONTH(Transaktionen!C$4:C$500)=MONTH(TODAY()))*(YEAR(Transaktionen!C$4:C$500)=YEAR(TODAY()))*Transaktionen!E$4:E$500)) | K18: =IF(OR(H18="",I18=0),"",IF(J18/I18>1,"OVER",IF(J18/I18>0.8,"WARN",TEXT(J18/I18,"0%"))))
B19: Jul | C19: =SUMPRODUCT((Transaktionen!D$4:D$500="Einnahme")*(MONTH(Transaktionen!C$4:C$500)=7)*(YEAR(Transaktionen!C$4:C$500)=YEAR(TODAY()))*Transaktionen!E$4:E$500) | D19: =SUMPRODUCT((Transaktionen!D$4:D$500="Ausgabe")*(MONTH(Transaktionen!C$4:C$500)=7)*(YEAR(Transaktionen!C$4:C$500)=YEAR(TODAY()))*Transaktionen!E$4:E$500) | E19: =C19-D19 | F19: =IF(C19=0,0,E19/C19) | H19: =IF(Budgets!B10="","",Budgets!B10) | I19: =IF(H19="","",Budgets!C10) | J19: =IF(H19="","",SUMPRODUCT((Transaktionen!D$4:D$500="Ausgabe")*(Transaktionen!F$4:F$500=H19)*(MONTH(Transaktionen!C$4:C$500)=MONTH(TODAY()))*(YEAR(Transaktionen!C$4:C$500)=YEAR(TODAY()))*Transaktionen!E$4:E$500)) | K19: =IF(OR(H19="",I19=0),"",IF(J19/I19>1,"OVER",IF(J19/I19>0.8,"WARN",TEXT(J19/I19,"0%"))))
B20: Aug | C20: =SUMPRODUCT((Transaktionen!D$4:D$500="Einnahme")*(MONTH(Transaktionen!C$4:C$500)=8)*(YEAR(Transaktionen!C$4:C$500)=YEAR(TODAY()))*Transaktionen!E$4:E$500) | D20: =SUMPRODUCT((Transaktionen!D$4:D$500="Ausgabe")*(MONTH(Transaktionen!C$4:C$500)=8)*(YEAR(Transaktionen!C$4:C$500)=YEAR(TODAY()))*Transaktionen!E$4:E$500) | E20: =C20-D20 | F20: =IF(C20=0,0,E20/C20) | H20: =IF(Budgets!B11="","",Budgets!B11) | I20: =IF(H20="","",Budgets!C11) | J20: =IF(H20="","",SUMPRODUCT((Transaktionen!D$4:D$500="Ausgabe")*(Transaktionen!F$4:F$500=H20)*(MONTH(Transaktionen!C$4:C$500)=MONTH(TODAY()))*(YEAR(Transaktionen!C$4:C$500)=YEAR(TODAY()))*Transaktionen!E$4:E$500)) | K20: =IF(OR(H20="",I20=0),"",IF(J20/I20>1,"OVER",IF(J20/I20>0.8,"WARN",TEXT(J20/I20,"0%"))))
B21: Sep | C21: =SUMPRODUCT((Transaktionen!D$4:D$500="Einnahme")*(MONTH(Transaktionen!C$4:C$500)=9)*(YEAR(Transaktionen!C$4:C$500)=YEAR(TODAY()))*Transaktionen!E$4:E$500) | D21: =SUMPRODUCT((Transaktionen!D$4:D$500="Ausgabe")*(MONTH(Transaktionen!C$4:C$500)=9)*(YEAR(Transaktionen!C$4:C$500)=YEAR(TODAY()))*Transaktionen!E$4:E$500) | E21: =C21-D21 | F21: =IF(C21=0,0,E21/C21) | H21: TOTAL | I21: =SUM(I13:I20) | J21: =SUM(J13:J20) | K21: =IF(I21=0,"",TEXT(J21/I21,"0%"))
B22: Okt | C22: =SUMPRODUCT((Transaktionen!D$4:D$500="Einnahme")*(MONTH(Transaktionen!C$4:C$500)=10)*(YEAR(Transaktionen!C$4:C$500)=YEAR(TODAY()))*Transaktionen!E$4:E$500) | D22: =SUMPRODUCT((Transaktionen!D$4:D$500="Ausgabe")*(MONTH(Transaktionen!C$4:C$500)=10)*(YEAR(Transaktionen!C$4:C$500)=YEAR(TODAY()))*Transaktionen!E$4:E$500) | E22: =C22-D22 | F22: =IF(C22=0,0,E22/C22)
B23: Nov | C23: =SUMPRODUCT((Transaktionen!D$4:D$500="Einnahme")*(MONTH(Transaktionen!C$4:C$500)=11)*(YEAR(Transaktionen!C$4:C$500)=YEAR(TODAY()))*Transaktionen!E$4:E$500) | D23: =SUMPRODUCT((Transaktionen!D$4:D$500="Ausgabe")*(MONTH(Transaktionen!C$4:C$500)=11)*(YEAR(Transaktionen!C$4:C$500)=YEAR(TODAY()))*Transaktionen!E$4:E$500) | E23: =C23-D23 | F23: =IF(C23=0,0,E23/C23)
B24: Dez | C24: =SUMPRODUCT((Transaktionen!D$4:D$500="Einnahme")*(MONTH(Transaktionen!C$4:C$500)=12)*(YEAR(Transaktionen!C$4:C$500)=YEAR(TODAY()))*Transaktionen!E$4:E$500) | D24: =SUMPRODUCT((Transaktionen!D$4:D$500="Ausgabe")*(MONTH(Transaktionen!C$4:C$500)=12)*(YEAR(Transaktionen!C$4:C$500)=YEAR(TODAY()))*Transaktionen!E$4:E$500) | E24: =C24-D24 | F24: =IF(C24=0,0,E24/C24)
B25: GESAMT | C25: =SUM(C13:C24) | D25: =SUM(D13:D24) | E25: =C25-D25 | F25: =IF(C25=0,0,E25/C25)
B27: KONTENÜBERSICHT
B28: Aktueller Stand aller Konten
B29: Konto | C29: Typ | D29: Startguthaben | E29: Einnahmen | F29: Ausgaben | G29: Aktueller Stand
B30: =IF(Konten!B4="","",Konten!B4) | C30: =IF(B30="","",Konten!C4) | D30: =IF(B30="","",Konten!D4) | E30: =IF(B30="","",Konten!E4) | F30: =IF(B30="","",Konten!F4) | G30: =IF(B30="","",Konten!G4)
B31: =IF(Konten!B5="","",Konten!B5) | C31: =IF(B31="","",Konten!C5) | D31: =IF(B31="","",Konten!D5) | E31: =IF(B31="","",Konten!E5) | F31: =IF(B31="","",Konten!F5) | G31: =IF(B31="","",Konten!G5)
B32: =IF(Konten!B6="","",Konten!B6) | C32: =IF(B32="","",Konten!C6) | D32: =IF(B32="","",Konten!D6) | E32: =IF(B32="","",Konten!E6) | F32: =IF(B32="","",Konten!F6) | G32: =IF(B32="","",Konten!G6)
B33: =IF(Konten!B7="","",Konten!B7) | C33: =IF(B33="","",Konten!C7) | D33: =IF(B33="","",Konten!D7) | E33: =IF(B33="","",Konten!E7) | F33: =IF(B33="","",Konten!F7) | G33: =IF(B33="","",Konten!G7)
B36: AUSGABEN NACH KATEGORIE | H36: LETZTE TRANSAKTIONEN
B37: Verteilung der Ausgaben im aktuellen Monat | H37: Die letzten 8 Buchungen
H38: Beschreibung | I38: Datum | J38: Betrag | K38: Typ
B39: =IF(H13="","",H13) | C39: =IF(B39="","",J13) | D39: =IF(OR(B39="",SUM(C$39:C$46)=0),"",C39/SUM(C$39:C$46)) | E39: =IF(D39="","",REPT("█",ROUND(D39*30,0))) | H39: =IF(Transaktionen!B4="","",Transaktionen!B4) | I39: =IF(H39="","",Transaktionen!C4) | J39: =IF(H39="","",Transaktionen!E4) | K39: =IF(H39="","",Transaktionen!D4)
B40: =IF(H14="","",H14) | C40: =IF(B40="","",J14) | D40: =IF(OR(B40="",SUM(C$39:C$46)=0),"",C40/SUM(C$39:C$46)) | E40: =IF(D40="","",REPT("█",ROUND(D40*30,0))) | H40: =IF(Transaktionen!B5="","",Transaktionen!B5) | I40: =IF(H40="","",Transaktionen!C5) | J40: =IF(H40="","",Transaktionen!E5) | K40: =IF(H40="","",Transaktionen!D5)
B41: =IF(H15="","",H15) | C41: =IF(B41="","",J15) | D41: =IF(OR(B41="",SUM(C$39:C$46)=0),"",C41/SUM(C$39:C$46)) | E41: =IF(D41="","",REPT("█",ROUND(D41*30,0))) | H41: =IF(Transaktionen!B6="","",Transaktionen!B6) | I41: =IF(H41="","",Transaktionen!C6) | J41: =IF(H41="","",Transaktionen!E6) | K41: =IF(H41="","",Transaktionen!D6)
B42: =IF(H16="","",H16) | C42: =IF(B42="","",J16) | D42: =IF(OR(B42="",SUM(C$39:C$46)=0),"",C42/SUM(C$39:C$46)) | E42: =IF(D42="","",REPT("█",ROUND(D42*30,0))) | H42: =IF(Transaktionen!B7="","",Transaktionen!B7) | I42: =IF(H42="","",Transaktionen!C7) | J42: =IF(H42="","",Transaktionen!E7) | K42: =IF(H42="","",Transaktionen!D7)
B43: =IF(H17="","",H17) | C43: =IF(B43="","",J17) | D43: =IF(OR(B43="",SUM(C$39:C$46)=0),"",C43/SUM(C$39:C$46)) | E43: =IF(D43="","",REPT("█",ROUND(D43*30,0))) | H43: =IF(Transaktionen!B8="","",Transaktionen!B8) | I43: =IF(H43="","",Transaktionen!C8) | J43: =IF(H43="","",Transaktionen!E8) | K43: =IF(H43="","",Transaktionen!D8)
B44: =IF(H18="","",H18) | C44: =IF(B44="","",J18) | D44: =IF(OR(B44="",SUM(C$39:C$46)=0),"",C44/SUM(C$39:C$46)) | E44: =IF(D44="","",REPT("█",ROUND(D44*30,0))) | H44: =IF(Transaktionen!B9="","",Transaktionen!B9) | I44: =IF(H44="","",Transaktionen!C9) | J44: =IF(H44="","",Transaktionen!E9) | K44: =IF(H44="","",Transaktionen!D9)
B45: =IF(H19="","",H19) | C45: =IF(B45="","",J19) | D45: =IF(OR(B45="",SUM(C$39:C$46)=0),"",C45/SUM(C$39:C$46)) | E45: =IF(D45="","",REPT("█",ROUND(D45*30,0))) | H45: =IF(Transaktionen!B10="","",Transaktionen!B10) | I45: =IF(H45="","",Transaktionen!C10) | J45: =IF(H45="","",Transaktionen!E10) | K45: =IF(H45="","",Transaktionen!D10)
B46: =IF(H20="","",H20) | C46: =IF(B46="","",J20) | D46: =IF(OR(B46="",SUM(C$39:C$46)=0),"",C46/SUM(C$39:C$46)) | E46: =IF(D46="","",REPT("█",ROUND(D46*30,0))) | H46: =IF(Transaktionen!B11="","",Transaktionen!B11) | I46: =IF(H46="","",Transaktionen!C11) | J46: =IF(H46="","",Transaktionen!E11) | K46: =IF(H46="","",Transaktionen!D11)
B48: DIAGRAMME
B65: Powered by Budget Tracker Pro · All data updates automatically

Sheet Transaktionen
B1: TRANSAKTIONEN
B3: Beschreibung | C3: Datum | D3: Typ | E3: Betrag | F3: Kategorie | G3: Konto | H3: Notizen
B4: Gehalt Februar | C4: 46054 | D4: Einnahme | E4: 3500 | F4: Gehalt | G4: Hauptkonto | H4: Monatsgehalt
B5: Freelance Projekt | C5: 46056 | D5: Einnahme | E5: 800 | F5: Freelance | G5: Hauptkonto | H5: Webdesign
B6: Miete | C6: 46054 | D6: Ausgabe | E6: 950 | F6: Wohnung | G6: Hauptkonto | H6: Monatsmiete
B7: Einkauf REWE | C7: 46058 | D7: Ausgabe | E7: 67.5 | F7: Lebensmittel | G7: Bargeld | H7: Wocheneinkauf
B8: Tankstelle | C8: 46060 | D8: Ausgabe | E8: 55 | F8: Transport | G8: Kreditkarte | H8: Benzin
B9: Netflix | C9: 46061 | D9: Ausgabe | E9: 12.99 | F9: Unterhaltung | G9: Hauptkonto | H9: Abo
B10: Arztbesuch | C10: 46063 | D10: Ausgabe | E10: 30 | F10: Gesundheit | G10: Hauptkonto | H10: Zuzahlung
B11: Restaurant Besuch | C11: 46065 | D11: Ausgabe | E11: 45.8 | F11: Restaurant | G11: Kreditkarte | H11: Abendessen
B12: Online Kurs | C12: 46067 | D12: Ausgabe | E12: 29.99 | F12: Bildung | G12: Kreditkarte | H12: Udemy
B13: Einkauf LIDL | C13: 46069 | D13: Ausgabe | E13: 43.2 | F13: Lebensmittel | G13: Bargeld | H13: Wocheneinkauf
B14: T-Shirt | C14: 46071 | D14: Ausgabe | E14: 25 | F14: Kleidung | G14: Kreditkarte | H14: H&M
B15: Dividende | C15: 46073 | D15: Einnahme | E15: 120 | F15: Investitionen | G15: Sparkonto | H15: ETF Ausschüttung

Sheet Kategorien
B1: KATEGORIEN
B3: Kategorie | C3: Typ | D3: Monatsbudget | E3: Farbe
B4: Gehalt | C4: Einnahme | D4: 0 | E4: Grün
B5: Freelance | C5: Einnahme | D5: 0 | E5: Blau
B6: Investitionen | C6: Einnahme | D6: 0 | E6: Lila
B7: Sonstiges Einkommen | C7: Einnahme | D7: 0 | E7: Grau
B8: Lebensmittel | C8: Ausgabe | D8: 400 | E8: Rot
B9: Transport | C9: Ausgabe | D9: 150 | E9: Orange
B10: Wohnung | C10: Ausgabe | D10: 1000 | E10: Gelb
B11: Unterhaltung | C11: Ausgabe | D11: 100 | E11: Pink
B12: Gesundheit | C12: Ausgabe | D12: 50 | E12: Türkis
B13: Bildung | C13: Ausgabe | D13: 50 | E13: Indigo
B14: Kleidung | C14: Ausgabe | D14: 80 | E14: Rosa
B15: Restaurant | C15: Ausgabe | D15: 100 | E15: Lila

Sheet Budgets
B1: MONATLICHE BUDGETS
B3: Kategorie | C3: Budget | D3: Ausgegeben | E3: Verbleibend | F3: Auslastung | G3: Status | H3: Fortschritt
B4: Lebensmittel | C4: 400 | D4: =SUMPRODUCT((Transaktionen!D$4:D$500="Ausgabe")*(Transaktionen!F$4:F$500=B4)*(MONTH(Transaktionen!C$4:C$500)=MONTH(TODAY()))*(YEAR(Transaktionen!C$4:C$500)=YEAR(TODAY()))*Transaktionen!E$4:E$500) | E4: =C4-D4 | F4: =IF(C4=0,0,D4/C4) | G4: =IF(C4=0,"—",IF(F4>1,"OVER",IF(F4>0.8,"WARN","OK"))) | H4: =IF(C4=0,"",REPT("█",MIN(ROUND(F4*20,0),20))&REPT("░",MAX(20-ROUND(F4*20,0),0)))
B5: Transport | C5: 150 | D5: =SUMPRODUCT((Transaktionen!D$4:D$500="Ausgabe")*(Transaktionen!F$4:F$500=B5)*(MONTH(Transaktionen!C$4:C$500)=MONTH(TODAY()))*(YEAR(Transaktionen!C$4:C$500)=YEAR(TODAY()))*Transaktionen!E$4:E$500) | E5: =C5-D5 | F5: =IF(C5=0,0,D5/C5) | G5: =IF(C5=0,"—",IF(F5>1,"OVER",IF(F5>0.8,"WARN","OK"))) | H5: =IF(C5=0,"",REPT("█",MIN(ROUND(F5*20,0),20))&REPT("░",MAX(20-ROUND(F5*20,0),0)))
B6: Wohnung | C6: 1000 | D6: =SUMPRODUCT((Transaktionen!D$4:D$500="Ausgabe")*(Transaktionen!F$4:F$500=B6)*(MONTH(Transaktionen!C$4:C$500)=MONTH(TODAY()))*(YEAR(Transaktionen!C$4:C$500)=YEAR(TODAY()))*Transaktionen!E$4:E$500) | E6: =C6-D6 | F6: =IF(C6=0,0,D6/C6) | G6: =IF(C6=0,"—",IF(F6>1,"OVER",IF(F6>0.8,"WARN","OK"))) | H6: =IF(C6=0,"",REPT("█",MIN(ROUND(F6*20,0),20))&REPT("░",MAX(20-ROUND(F6*20,0),0)))
B7: Unterhaltung | C7: 100 | D7: =SUMPRODUCT((Transaktionen!D$4:D$500="Ausgabe")*(Transaktionen!F$4:F$500=B7)*(MONTH(Transaktionen!C$4:C$500)=MONTH(TODAY()))*(YEAR(Transaktionen!C$4:C$500)=YEAR(TODAY()))*Transaktionen!E$4:E$500) | E7: =C7-D7 | F7: =IF(C7=0,0,D7/C7) | G7: =IF(C7=0,"—",IF(F7>1,"OVER",IF(F7>0.8,"WARN","OK"))) | H7: =IF(C7=0,"",REPT("█",MIN(ROUND(F7*20,0),20))&REPT("░",MAX(20-ROUND(F7*20,0),0)))
B8: Gesundheit | C8: 50 | D8: =SUMPRODUCT((Transaktionen!D$4:D$500="Ausgabe")*(Transaktionen!F$4:F$500=B8)*(MONTH(Transaktionen!C$4:C$500)=MONTH(TODAY()))*(YEAR(Transaktionen!C$4:C$500)=YEAR(TODAY()))*Transaktionen!E$4:E$500) | E8: =C8-D8 | F8: =IF(C8=0,0,D8/C8) | G8: =IF(C8=0,"—",IF(F8>1,"OVER",IF(F8>0.8,"WARN","OK"))) | H8: =IF(C8=0,"",REPT("█",MIN(ROUND(F8*20,0),20))&REPT("░",MAX(20-ROUND(F8*20,0),0)))
B9: Bildung | C9: 50 | D9: =SUMPRODUCT((Transaktionen!D$4:D$500="Ausgabe")*(Transaktionen!F$4:F$500=B9)*(MONTH(Transaktionen!C$4:C$500)=MONTH(TODAY()))*(YEAR(Transaktionen!C$4:C$500)=YEAR(TODAY()))*Transaktionen!E$4:E$500) | E9: =C9-D9 | F9: =IF(C9=0,0,D9/C9) | G9: =IF(C9=0,"—",IF(F9>1,"OVER",IF(F9>0.8,"WARN","OK"))) | H9: =IF(C9=0,"",REPT("█",MIN(ROUND(F9*20,0),20))&REPT("░",MAX(20-ROUND(F9*20,0),0)))
B10: Kleidung | C10: 80 | D10: =SUMPRODUCT((Transaktionen!D$4:D$500="Ausgabe")*(Transaktionen!F$4:F$500=B10)*(MONTH(Transaktionen!C$4:C$500)=MONTH(TODAY()))*(YEAR(Transaktionen!C$4:C$500)=YEAR(TODAY()))*Transaktionen!E$4:E$500) | E10: =C10-D10 | F10: =IF(C10=0,0,D10/C10) | G10: =IF(C10=0,"—",IF(F10>1,"OVER",IF(F10>0.8,"WARN","OK"))) | H10: =IF(C10=0,"",REPT("█",MIN(ROUND(F10*20,0),20))&REPT("░",MAX(20-ROUND(F10*20,0),0)))
B11: Restaurant | C11: 100 | D11: =SUMPRODUCT((Transaktionen!D$4:D$500="Ausgabe")*(Transaktionen!F$4:F$500=B11)*(MONTH(Transaktionen!C$4:C$500)=MONTH(TODAY()))*(YEAR(Transaktionen!C$4:C$500)=YEAR(TODAY()))*Transaktionen!E$4:E$500) | E11: =C11-D11 | F11: =IF(C11=0,0,D11/C11) | G11: =IF(C11=0,"—",IF(F11>1,"OVER",IF(F11>0.8,"WARN","OK"))) | H11: =IF(C11=0,"",REPT("█",MIN(ROUND(F11*20,0),20))&REPT("░",MAX(20-ROUND(F11*20,0),0)))
B12: TOTAL | C12: =SUM(C4:C11) | D12: =SUM(D4:D11) | E12: =C12-D12 | F12: =IF(C12=0,0,D12/C12)

Sheet Konten
B1: KONTEN
B3: Kontoname | C3: Typ | D3: Startguthaben | E3: Einnahmen | F3: Ausgaben | G3: Aktueller Stand
B4: Hauptkonto | C4: Bank | D4: 2500 | E4: =SUMPRODUCT((Transaktionen!D$4:D$500="Einnahme")*(Transaktionen!G$4:G$500=B4)*Transaktionen!E$4:E$500) | F4: =SUMPRODUCT((Transaktionen!D$4:D$500="Ausgabe")*(Transaktionen!G$4:G$500=B4)*Transaktionen!E$4:E$500) | G4: =D4+E4-F4
B5: Bargeld | C5: Bargeld | D5: 200 | E5: =SUMPRODUCT((Transaktionen!D$4:D$500="Einnahme")*(Transaktionen!G$4:G$500=B5)*Transaktionen!E$4:E$500) | F5: =SUMPRODUCT((Transaktionen!D$4:D$500="Ausgabe")*(Transaktionen!G$4:G$500=B5)*Transaktionen!E$4:E$500) | G5: =D5+E5-F5
B6: Kreditkarte | C6: Kreditkarte | D6: 0 | E6: =SUMPRODUCT((Transaktionen!D$4:D$500="Einnahme")*(Transaktionen!G$4:G$500=B6)*Transaktionen!E$4:E$500) | F6: =SUMPRODUCT((Transaktionen!D$4:D$500="Ausgabe")*(Transaktionen!G$4:G$500=B6)*Transaktionen!E$4:E$500) | G6: =D6+E6-F6
B7: Sparkonto | C7: Sparkonto | D7: 5000 | E7: =SUMPRODUCT((Transaktionen!D$4:D$500="Einnahme")*(Transaktionen!G$4:G$500=B7)*Transaktionen!E$4:E$500) | F7: =SUMPRODUCT((Transaktionen!D$4:D$500="Ausgabe")*(Transaktionen!G$4:G$500=B7)*Transaktionen!E$4:E$500) | G7: =D7+E7-F7
E8: =IF(B8="","",SUMPRODUCT((Transaktionen!D$4:D$500="Einnahme")*(Transaktionen!G$4:G$500=B8)*Transaktionen!E$4:E$500)) | F8: =IF(B8="","",SUMPRODUCT((Transaktionen!D$4:D$500="Ausgabe")*(Transaktionen!G$4:G$500=B8)*Transaktionen!E$4:E$500)) | G8: =IF(B8="","",D8+E8-F8)
E9: =IF(B9="","",SUMPRODUCT((Transaktionen!D$4:D$500="Einnahme")*(Transaktionen!G$4:G$500=B9)*Transaktionen!E$4:E$500)) | F9: =IF(B9="","",SUMPRODUCT((Transaktionen!D$4:D$500="Ausgabe")*(Transaktionen!G$4:G$500=B9)*Transaktionen!E$4:E$500)) | G9: =IF(B9="","",D9+E9-F9)
E10: =IF(B10="","",SUMPRODUCT((Transaktionen!D$4:D$500="Einnahme")*(Transaktionen!G$4:G$500=B10)*Transaktionen!E$4:E$500)) | F10: =IF(B10="","",SUMPRODUCT((Transaktionen!D$4:D$500="Ausgabe")*(Transaktionen!G$4:G$500=B10)*Transaktionen!E$4:E$500)) | G10: =IF(B10="","",D10+E10-F10)
E11: =IF(B11="","",SUMPRODUCT((Transaktionen!D$4:D$500="Einnahme")*(Transaktionen!G$4:G$500=B11)*Transaktionen!E$4:E$500)) | F11: =IF(B11="","",SUMPRODUCT((Transaktionen!D$4:D$500="Ausgabe")*(Transaktionen!G$4:G$500=B11)*Transaktionen!E$4:E$500)) | G11: =IF(B11="","",D11+E11-F11)
B15: TOTAL | D15: =SUM(D4:D11) | E15: =SUM(E4:E11) | F15: =SUM(F4:F11) | G15: =SUM(G4:G11)

Sheet Anleitung
B1: BUDGET TRACKER PRO
B2: Anleitung & Schnellstart
B4: SO FUNKTIONIERT ES:
B6: 1. TRANSAKTIONEN
B7: Trage jede Einnahme und Ausgabe im Tab 'Transaktionen' ein.
B8: Nutze die Dropdown-Menüs für Typ, Kategorie und Konto.
B10: 2. KATEGORIEN
B11: Passe deine Kategorien an oder füge neue hinzu.
B12: Setze Monatsbudgets für Ausgabe-Kategorien.
B14: 3. BUDGETS
B15: Sieh auf einen Blick, ob du im Budget bist.
B16: Fortschrittsbalken und Ampel-Status zeigen deinen Stand.
... B26: TIPP: Lösche die Beispieldaten und starte mit deinen eigenen!
